{
  "run_id": "20260411_150310_705527",
  "scenario_name": "area_20260411_150310_705527",
  "sumocfg_path": "C:\\Users\\santhosh\\OneDrive\\Desktop\\trafiic pro\\web_runs\\20260411_150310_705527\\area.sumocfg",
  "net_path": "C:\\Users\\santhosh\\OneDrive\\Desktop\\trafiic pro\\web_runs\\20260411_150310_705527\\area.net.xml",
  "route_path": "C:\\Users\\santhosh\\OneDrive\\Desktop\\trafiic pro\\web_runs\\20260411_150310_705527\\area.rou.xml",
  "source": "area-layout",
  "fallback_reason": null,
  "user_message": "Created a simplified area network with 2 rows and 3 columns of junctions.",
  "bbox": {
    "south": 13.09793316719351,
    "north": 13.103283363754686,
    "west": 80.19126892089845,
    "east": 80.19813537597658
  },
  "polygon": [
    {
      "lat": 13.09793316719351,
      "lng": 80.19126892089845
    },
    {
      "lat": 13.103283363754686,
      "lng": 80.19126892089845
    },
    {
      "lat": 13.103283363754686,
      "lng": 80.19813537597658
    },
    {
      "lat": 13.09793316719351,
      "lng": 80.19813537597658
    }
  ],
  "preview": {
    "nodes": [
      {
        "id": "E0",
        "x": 900.0,
        "y": 128.43,
        "type": "priority"
      },
      {
        "id": "J0_2",
        "x": 763.35,
        "y": 128.43,
        "type": "traffic_light"
      },
      {
        "id": "E1",
        "x": 900.0,
        "y": 570.9,
        "type": "priority"
      },
      {
        "id": "J1_2",
        "x": 801.77,
        "y": 570.9,
        "type": "traffic_light"
      },
      {
        "id": "J0_0",
        "x": 140.0,
        "y": 104.58,
        "type": "traffic_light"
      },
      {
        "id": "J0_1",
        "x": 453.1,
        "y": 106.93,
        "type": "traffic_light"
      },
      {
        "id": "J1_0",
        "x": 103.35,
        "y": 589.43,
        "type": "traffic_light"
      },
      {
        "id": "N0",
        "x": 140.0,
        "y": 0.0,
        "type": "priority"
      },
      {
        "id": "W0",
        "x": 0.0,
        "y": 104.58,
        "type": "priority"
      },
      {
        "id": "J1_1",
        "x": 443.85,
        "y": 581.97,
        "type": "traffic_light"
      },
      {
        "id": "N1",
        "x": 453.1,
        "y": 0.0,
        "type": "priority"
      },
      {
        "id": "N2",
        "x": 763.35,
        "y": 0.0,
        "type": "priority"
      },
      {
        "id": "S0",
        "x": 103.35,
        "y": 701.0,
        "type": "priority"
      },
      {
        "id": "W1",
        "x": 0.0,
        "y": 589.43,
        "type": "priority"
      },
      {
        "id": "S1",
        "x": 443.85,
        "y": 701.0,
        "type": "priority"
      },
      {
        "id": "S2",
        "x": 801.77,
        "y": 701.0,
        "type": "priority"
      }
    ],
    "edges": [
      {
        "id": "E0_to_J0_2",
        "from": "E0",
        "to": "J0_2",
        "lanes": 2,
        "shape": [
          {
            "x": 900.0,
            "y": 131.63
          },
          {
            "x": 774.33,
            "y": 131.63
          }
        ]
      },
      {
        "id": "E1_to_J1_2",
        "from": "E1",
        "to": "J1_2",
        "lanes": 2,
        "shape": [
          {
            "x": 900.0,
            "y": 574.1
          },
          {
            "x": 812.17,
            "y": 574.1
          }
        ]
      },
      {
        "id": "J0_0_to_J0_1",
        "from": "J0_0",
        "to": "J0_1",
        "lanes": 2,
        "shape": [
          {
            "x": 150.375,
            "y": 101.46000000000001
          },
          {
            "x": 442.65,
            "y": 103.65
          }
        ]
      },
      {
        "id": "J0_0_to_J1_0",
        "from": "J0_0",
        "to": "J1_0",
        "lanes": 2,
        "shape": [
          {
            "x": 142.365,
            "y": 115.69
          },
          {
            "x": 107.375,
            "y": 578.65
          }
        ]
      },
      {
        "id": "J0_0_to_N0",
        "from": "J0_0",
        "to": "N0",
        "lanes": 2,
        "shape": [
          {
            "x": 136.8,
            "y": 94.18
          },
          {
            "x": 136.8,
            "y": 0.0
          }
        ]
      },
      {
        "id": "J0_0_to_W0",
        "from": "J0_0",
        "to": "W0",
        "lanes": 2,
        "shape": [
          {
            "x": 129.1,
            "y": 107.78
          },
          {
            "x": 0.0,
            "y": 107.78
          }
        ]
      },
      {
        "id": "J0_1_to_J0_0",
        "from": "J0_1",
        "to": "J0_0",
        "lanes": 2,
        "shape": [
          {
            "x": 442.6,
            "y": 110.05000000000001
          },
          {
            "x": 150.32999999999998,
            "y": 107.86
          }
        ]
      },
      {
        "id": "J0_1_to_J0_2",
        "from": "J0_1",
        "to": "J0_2",
        "lanes": 2,
        "shape": [
          {
            "x": 464.02,
            "y": 104.47999999999999
          },
          {
            "x": 752.74,
            "y": 124.485
          }
        ]
      },
      {
        "id": "J0_1_to_J1_1",
        "from": "J0_1",
        "to": "J1_1",
        "lanes": 2,
        "shape": [
          {
            "x": 456.09000000000003,
            "y": 117.72
          },
          {
            "x": 447.26,
            "y": 571.3
          }
        ]
      },
      {
        "id": "J0_1_to_N1",
        "from": "J0_1",
        "to": "N1",
        "lanes": 2,
        "shape": [
          {
            "x": 449.9,
            "y": 96.48
          },
          {
            "x": 449.9,
            "y": 0.0
          }
        ]
      },
      {
        "id": "J0_2_to_E0",
        "from": "J0_2",
        "to": "E0",
        "lanes": 2,
        "shape": [
          {
            "x": 774.33,
            "y": 125.22999999999999
          },
          {
            "x": 900.0,
            "y": 125.22999999999999
          }
        ]
      },
      {
        "id": "J0_2_to_J0_1",
        "from": "J0_2",
        "to": "J0_1",
        "lanes": 2,
        "shape": [
          {
            "x": 752.3,
            "y": 130.875
          },
          {
            "x": 463.58000000000004,
            "y": 110.865
          }
        ]
      },
      {
        "id": "J0_2_to_J1_2",
        "from": "J0_2",
        "to": "J1_2",
        "lanes": 2,
        "shape": [
          {
            "x": 767.485,
            "y": 139.08999999999997
          },
          {
            "x": 804.025,
            "y": 559.9
          }
        ]
      },
      {
        "id": "J0_2_to_N2",
        "from": "J0_2",
        "to": "N2",
        "lanes": 2,
        "shape": [
          {
            "x": 760.15,
            "y": 117.57
          },
          {
            "x": 760.15,
            "y": 0.0
          }
        ]
      },
      {
        "id": "J1_0_to_J0_0",
        "from": "J1_0",
        "to": "J0_0",
        "lanes": 2,
        "shape": [
          {
            "x": 100.995,
            "y": 578.165
          },
          {
            "x": 135.985,
            "y": 115.21000000000001
          }
        ]
      },
      {
        "id": "J1_0_to_J1_1",
        "from": "J1_0",
        "to": "J1_1",
        "lanes": 2,
        "shape": [
          {
            "x": 114.33500000000001,
            "y": 585.99
          },
          {
            "x": 433.245,
            "y": 579.0
          }
        ]
      },
      {
        "id": "J1_0_to_S0",
        "from": "J1_0",
        "to": "S0",
        "lanes": 2,
        "shape": [
          {
            "x": 106.55000000000001,
            "y": 599.83
          },
          {
            "x": 106.55000000000001,
            "y": 701.0
          }
        ]
      },
      {
        "id": "J1_0_to_W1",
        "from": "J1_0",
        "to": "W1",
        "lanes": 2,
        "shape": [
          {
            "x": 92.95,
            "y": 592.63
          },
          {
            "x": 0.0,
            "y": 592.63
          }
        ]
      },
      {
        "id": "J1_1_to_J0_1",
        "from": "J1_1",
        "to": "J0_1",
        "lanes": 2,
        "shape": [
          {
            "x": 440.86,
            "y": 571.1800000000001
          },
          {
            "x": 449.69,
            "y": 117.59
          }
        ]
      },
      {
        "id": "J1_1_to_J1_0",
        "from": "J1_1",
        "to": "J1_0",
        "lanes": 2,
        "shape": [
          {
            "x": 433.385,
            "y": 585.4
          },
          {
            "x": 114.475,
            "y": 592.39
          }
        ]
      },
      {
        "id": "J1_1_to_J1_2",
        "from": "J1_1",
        "to": "J1_2",
        "lanes": 2,
        "shape": [
          {
            "x": 454.48,
            "y": 578.44
          },
          {
            "x": 790.9100000000001,
            "y": 568.0350000000001
          }
        ]
      },
      {
        "id": "J1_1_to_S1",
        "from": "J1_1",
        "to": "S1",
        "lanes": 2,
        "shape": [
          {
            "x": 447.04999999999995,
            "y": 592.51
          },
          {
            "x": 447.04999999999995,
            "y": 701.0
          }
        ]
      },
      {
        "id": "J1_2_to_E1",
        "from": "J1_2",
        "to": "E1",
        "lanes": 2,
        "shape": [
          {
            "x": 812.17,
            "y": 567.7
          },
          {
            "x": 900.0,
            "y": 567.7
          }
        ]
      },
      {
        "id": "J1_2_to_J0_2",
        "from": "J1_2",
        "to": "J0_2",
        "lanes": 2,
        "shape": [
          {
            "x": 797.65,
            "y": 560.45
          },
          {
            "x": 761.115,
            "y": 139.64499999999998
          }
        ]
      },
      {
        "id": "J1_2_to_J1_1",
        "from": "J1_2",
        "to": "J1_1",
        "lanes": 2,
        "shape": [
          {
            "x": 791.1099999999999,
            "y": 574.4300000000001
          },
          {
            "x": 454.675,
            "y": 584.84
          }
        ]
      },
      {
        "id": "J1_2_to_S2",
        "from": "J1_2",
        "to": "S2",
        "lanes": 2,
        "shape": [
          {
            "x": 804.97,
            "y": 581.5
          },
          {
            "x": 804.97,
            "y": 701.0
          }
        ]
      },
      {
        "id": "N0_to_J0_0",
        "from": "N0",
        "to": "J0_0",
        "lanes": 2,
        "shape": [
          {
            "x": 143.2,
            "y": 0.0
          },
          {
            "x": 143.2,
            "y": 94.18
          }
        ]
      },
      {
        "id": "N1_to_J0_1",
        "from": "N1",
        "to": "J0_1",
        "lanes": 2,
        "shape": [
          {
            "x": 456.29999999999995,
            "y": 0.0
          },
          {
            "x": 456.29999999999995,
            "y": 96.48
          }
        ]
      },
      {
        "id": "N2_to_J0_2",
        "from": "N2",
        "to": "J0_2",
        "lanes": 2,
        "shape": [
          {
            "x": 766.55,
            "y": 0.0
          },
          {
            "x": 766.55,
            "y": 117.57
          }
        ]
      },
      {
        "id": "S0_to_J1_0",
        "from": "S0",
        "to": "J1_0",
        "lanes": 2,
        "shape": [
          {
            "x": 100.15,
            "y": 701.0
          },
          {
            "x": 100.15,
            "y": 599.83
          }
        ]
      },
      {
        "id": "S1_to_J1_1",
        "from": "S1",
        "to": "J1_1",
        "lanes": 2,
        "shape": [
          {
            "x": 440.65,
            "y": 701.0
          },
          {
            "x": 440.65,
            "y": 592.51
          }
        ]
      },
      {
        "id": "S2_to_J1_2",
        "from": "S2",
        "to": "J1_2",
        "lanes": 2,
        "shape": [
          {
            "x": 798.5699999999999,
            "y": 701.0
          },
          {
            "x": 798.5699999999999,
            "y": 581.5
          }
        ]
      },
      {
        "id": "W0_to_J0_0",
        "from": "W0",
        "to": "J0_0",
        "lanes": 2,
        "shape": [
          {
            "x": 0.0,
            "y": 101.38
          },
          {
            "x": 129.1,
            "y": 101.38
          }
        ]
      },
      {
        "id": "W1_to_J1_0",
        "from": "W1",
        "to": "J1_0",
        "lanes": 2,
        "shape": [
          {
            "x": 0.0,
            "y": 586.23
          },
          {
            "x": 92.95,
            "y": 586.23
          }
        ]
      }
    ],
    "bounds": {
      "min_x": 0.0,
      "max_x": 900.0,
      "min_y": 0.0,
      "max_y": 701.0
    }
  },
  "layout": {
    "rows": 2,
    "cols": 3,
    "width": 900,
    "height": 701
  }
}